parsehole/__init__.py
parseholetest-0.1.dist-info/LICENSE
parseholetest-0.1.dist-info/METADATA
parseholetest-0.1.dist-info/WHEEL
parseholetest-0.1.dist-info/top_level.txt
parseholetest-0.1.dist-info/RECORD
