Metadata-Version: 2.1
Name: parseholetest
Version: 0.1
Summary: Sentence conjunction parsing package
Home-page: https://github.com/vaustin33/parsehole
Author: Victoria Austin
Author-email: victoriaaustin97@gmail.com
License: UNKNOWN
Platform: UNKNOWN
Classifier: Programming Language :: Python :: 3
Classifier: License :: OSI Approved :: MIT License
Classifier: Operating System :: OS Independent
